{"zipper":{"tag":"NameFocus","args":[{"right":"","left":"Widgets"},[{"body":{"tag":"Markdown","args":["# Widgets\n\n## Sliders\n\nSliders are a UI element that evaluate to a number between 0 and 1."]},"id":19},{"body":{"tag":"Named","args":["slider",{"tag":"Slider","args":[0.18125]}]},"id":20},{"body":{"tag":"Named","args":["slider-value",{"tag":"Expression","args":[[{"tag":"Value","args":["slider"]}]]}]},"id":21},{"body":{"tag":"Markdown","args":["## Graphs\n\n`plot:function` takes a function as an argument and displays a continuous graph."]},"id":22},{"body":{"tag":"Named","args":["",{"tag":"Expression","args":[[{"tag":"Value","args":["plot:function"]},{"tag":"Lambda","args":["x",[{"tag":"Value","args":["x"]}]]},{"tag":"Value","args":["-1"]},{"tag":"Value","args":["1"]},{"tag":"Value","args":["-1"]},{"tag":"Value","args":["1"]}]]}]},"id":23},{"body":{"tag":"Markdown","args":["## Audio\n\nThe `audio:play-buffer` takes a `f32-array` and interprets it as audio at `audio:sample-rate`."]},"id":27},{"body":{"tag":"Named","args":["",{"tag":"Expression","args":[[{"tag":"Value","args":["audio:play-buffer"]},{"tag":"SubExp","args":[[{"tag":"Value","args":["f32-array:make"]},{"tag":"Lambda","args":["x",[{"tag":"Value","args":["0.1"]},{"tag":"Value","args":["*"]},{"tag":"Value","args":["sin"]},{"tag":"SubExp","args":[[{"tag":"Value","args":["x"]},{"tag":"Value","args":["*"]},{"tag":"Value","args":["440"]},{"tag":"Value","args":["*"]},{"tag":"Value","args":["pi"]},{"tag":"Value","args":["*"]},{"tag":"Value","args":["2"]},{"tag":"Value","args":["/"]},{"tag":"Value","args":["audio:sample-rate"]}]]}]]},{"tag":"Value","args":["audio:sample-rate"]}]]}]]}]},"id":28}]]},"nextId":30,"id":null,"projectName":"Widgets"}